hwcomponents_cacti/__init__.py
hwcomponents_cacti/_version.py
hwcomponents_cacti/default_cfg.cfg
hwcomponents_cacti/hwcomponents_cacti.py
hwcomponents_cacti/cacti/2DDRAM_Samsung2GbDDR2.cfg
hwcomponents_cacti/cacti/2DDRAM_micron1Gb.cfg
hwcomponents_cacti/cacti/3DDRAM_Samsung3D8Gb_extened.cfg
hwcomponents_cacti/cacti/README
hwcomponents_cacti/cacti/TSV.cc
hwcomponents_cacti/cacti/TSV.h
hwcomponents_cacti/cacti/Ucache.cc
hwcomponents_cacti/cacti/Ucache.h
hwcomponents_cacti/cacti/arbiter.cc
hwcomponents_cacti/cacti/arbiter.h
hwcomponents_cacti/cacti/area.cc
hwcomponents_cacti/cacti/area.h
hwcomponents_cacti/cacti/bank.cc
hwcomponents_cacti/cacti/bank.h
hwcomponents_cacti/cacti/basic_circuit.cc
hwcomponents_cacti/cacti/basic_circuit.h
hwcomponents_cacti/cacti/cache.cfg
hwcomponents_cacti/cacti/cacti
hwcomponents_cacti/cacti/cacti.i
hwcomponents_cacti/cacti/cacti.mk
hwcomponents_cacti/cacti/cacti_interface.cc
hwcomponents_cacti/cacti/cacti_interface.h
hwcomponents_cacti/cacti/component.cc
hwcomponents_cacti/cacti/component.h
hwcomponents_cacti/cacti/const.h
hwcomponents_cacti/cacti/contention.dat
hwcomponents_cacti/cacti/crossbar.cc
hwcomponents_cacti/cacti/crossbar.h
hwcomponents_cacti/cacti/ddr3.cfg
hwcomponents_cacti/cacti/decoder.cc
hwcomponents_cacti/cacti/decoder.h
hwcomponents_cacti/cacti/dram.cfg
hwcomponents_cacti/cacti/extio.cc
hwcomponents_cacti/cacti/extio.h
hwcomponents_cacti/cacti/extio_technology.cc
hwcomponents_cacti/cacti/extio_technology.h
hwcomponents_cacti/cacti/htree2.cc
hwcomponents_cacti/cacti/htree2.h
hwcomponents_cacti/cacti/io.cc
hwcomponents_cacti/cacti/io.h
hwcomponents_cacti/cacti/lpddr.cfg
hwcomponents_cacti/cacti/main.cc
hwcomponents_cacti/cacti/makefile
hwcomponents_cacti/cacti/mat.cc
hwcomponents_cacti/cacti/mat.h
hwcomponents_cacti/cacti/memcad.cc
hwcomponents_cacti/cacti/memcad.h
hwcomponents_cacti/cacti/memcad_parameters.cc
hwcomponents_cacti/cacti/memcad_parameters.h
hwcomponents_cacti/cacti/memorybus.cc
hwcomponents_cacti-1.0.28.dist-info/METADATA
hwcomponents_cacti-1.0.28.dist-info/WHEEL
hwcomponents_cacti-1.0.28.dist-info/top_level.txt
hwcomponents_cacti-1.0.28.dist-info/RECORD
