Metadata-Version: 2.4
Name: hwcomponents_cacti
Version: 1.0.28
Summary: A package for estimating the energy and area of memories with CACTI
Author-email: Tanner Andrulis <andrulis@mit.edu>
License-Expression: MIT
Keywords: accelerator,hardware,energy,estimation,CACTI
Classifier: Development Status :: 3 - Alpha
Classifier: Programming Language :: Python :: 3
Classifier: Topic :: Scientific/Engineering :: Electronic Design Automation (EDA)
Requires-Python: >=3.12
Requires-Dist: hwcomponents
